shikkoku/__init__.py
shikkoku/animation.py
shikkoku/app.py
shikkoku/color.py
shikkoku/engine.py
shikkoku/sample_main.py
shikkoku/sample_scene.py
shikkoku/text_formatter.py
shikkoku/resources/__init__.py
shikkoku-0.0.4.dist-info/LICENSE
shikkoku-0.0.4.dist-info/METADATA
shikkoku-0.0.4.dist-info/WHEEL
shikkoku-0.0.4.dist-info/top_level.txt
shikkoku-0.0.4.dist-info/RECORD
