Metadata-Version: 2.1
Name: shikkoku
Version: 0.0.4
Summary: A small engine for game-making wrapped around SDL2
Author-email: James Correll <mail.james.correll@gmail.com>
Classifier: Programming Language :: Python :: 3
Requires-Python: >=3.9
License-File: LICENSE
Requires-Dist: pysdl2
Requires-Dist: pysdl2-dll
Requires-Dist: pillow
